img2ascii/__init__.py
img2ascii/main.py
img2ascii_cli-1.0.0.dist-info/METADATA
img2ascii_cli-1.0.0.dist-info/WHEEL
img2ascii_cli-1.0.0.dist-info/entry_points.txt
img2ascii_cli-1.0.0.dist-info/top_level.txt
img2ascii_cli-1.0.0.dist-info/RECORD
